MANIFEST.in
README.rst
entry_points.ini
setup.cfg
setup.py
src/AnthraxDojoFrontend.egg-info/PKG-INFO
src/AnthraxDojoFrontend.egg-info/SOURCES.txt
src/AnthraxDojoFrontend.egg-info/dependency_links.txt
src/AnthraxDojoFrontend.egg-info/entry_points.txt
src/AnthraxDojoFrontend.egg-info/namespace_packages.txt
src/AnthraxDojoFrontend.egg-info/requires.txt
src/AnthraxDojoFrontend.egg-info/top_level.txt
src/anthrax/__init__.py
src/anthrax/dojo/__init__.py
src/anthrax/dojo/frontend.py
src/anthrax/dojo/view.py
src/anthrax/dojo/view_helpers.py
src/anthrax/dojo/templates/anthrax_datebox.mako
src/anthrax/dojo/templates/anthrax_text_box.mako
src/anthrax/dojo/templates/button.mako
src/anthrax/dojo/templates/editor.mako
src/anthrax/dojo/templates/file_upload.mako
src/anthrax/dojo/templates/hidden.mako
src/anthrax/dojo/templates/spinner.mako
src/anthrax/dojo/templates/tabular_form.mako
src/anthrax/dojo/templates/textarea.mako