Metadata-Version: 1.1
Name: AnthraxDojoFrontend
Version: 0.1.0
Summary: Anthrax frontend for using dojo toolkit
Home-page: http://github.com/zefciu/Anthrax
Author: Szymon Pyżalski
Author-email: zefciu <szymon@pythonista.net>
License: UNKNOWN
Keywords: form web javascript ajax validation wysiwyg
Platform: UNKNOWN
Classifier: Development Status :: 3 - Alpha
Classifier: Intended Audience :: Developers
Classifier: License :: OSI Approved :: BSD License
Classifier: Programming Language :: Python :: 3
Classifier: Programming Language :: Python :: 3.2
Classifier: Topic :: Internet :: WWW/HTTP :: Dynamic Content
